activity_browser/__init__.py
activity_browser-0.0.0.dist-info/METADATA
activity_browser-0.0.0.dist-info/WHEEL
activity_browser-0.0.0.dist-info/licenses/LICENSE
activity_browser-0.0.0.dist-info/RECORD
