Metadata-Version: 2.3
Name: activity-browser
Version: 0.0.0
Summary: Placeholder package for the Brightway2 GUI: Activity Browser
Author-email: Marin Visscher <m.r.visscher@cml.leidenuniv.nl>
License-File: LICENSE
Classifier: Development Status :: 1 - Planning
Requires-Python: >=3.8
